aidkit/LICENSE
aidkit/README.md
aidkit/__init__.py
aidkit/main.py
aidkit/py.typed
aidkit/tests/__init__.py
smighty/__init__.py
smighty/__main__.py
smighty/app/__init__.py
smighty/app/base.py
smighty/app/cli/__init__.py
smighty/app/cli/__main__.py
smighty/app/cli/welcome.py
smighty/app/consts.py
smighty/app/main.py
smighty/app/tests/__init__.py
smighty/app/tests/test_cli_main.py
smighty/app/tests/test_main.py
smighty/app/tests/test_welcome.py
smighty/app/ui/__init__.py
smighty/app/ui/__main__.py
smighty/app/ui/chat.ipynb
smighty/app/ui/chat.py
smighty/app/ui/llmchat.py
smighty/notebooks/base_setup.ipynb
smighty/py.typed
smighty/root.py
smighty/tests/__init__.py
smighty/tests/test_base.py
smighty/utils/__init__.py
smighty/utils/validate.py
smighty-0.0.3.dist-info/LICENSE
smighty-0.0.3.dist-info/METADATA
smighty-0.0.3.dist-info/WHEEL
smighty-0.0.3.dist-info/RECORD
