Metadata-Version: 2.1
Name: smighty
Version: 0.0.3
Summary: Small, yet powerful conversational agent framework
License: Creative Commons Attribution-NonCommercial-ShareAlike 4.0 International Public License
Author: Al Wonder
Author-email: al@yiwonder.com
Requires-Python: >=3.10,<4.0
Classifier: License :: Other/Proprietary License
Classifier: Programming Language :: Python :: 3
Classifier: Programming Language :: Python :: 3.10
Classifier: Programming Language :: Python :: 3.11
Classifier: Programming Language :: Python :: 3.12
Provides-Extra: all
Provides-Extra: cli
Provides-Extra: ui
Requires-Dist: gradio (>=4.7.1,<5.0.0) ; extra == "all" or extra == "ui"
Requires-Dist: openapi[all] (>=1.1.0,<2.0.0)
Requires-Dist: pydantic-settings (>=2.1.0,<3.0.0)
Requires-Dist: typer[all] (>=0.9.0,<0.10.0) ; extra == "all" or extra == "cli"
